archetypal/__init__.py
archetypal/cli.py
archetypal/dataportal.py
archetypal/eplus_interface/__init__.py
archetypal/eplus_interface/basement.py
archetypal/eplus_interface/energy_plus.py
archetypal/eplus_interface/exceptions.py
archetypal/eplus_interface/expand_objects.py
archetypal/eplus_interface/slab.py
archetypal/eplus_interface/transition.py
archetypal/eplus_interface/version.py
archetypal/idfclass/__init__.py
archetypal/idfclass/end_use_balance.py
archetypal/idfclass/extensions.py
archetypal/idfclass/idf.py
archetypal/idfclass/load_balance.py
archetypal/idfclass/meters.py
archetypal/idfclass/outputs.py
archetypal/idfclass/reports.py
archetypal/idfclass/sql.py
archetypal/idfclass/util.py
archetypal/idfclass/variables.py
archetypal/plot.py
archetypal/py.typed
archetypal/reportdata.py
archetypal/schedule.py
archetypal/simple_glazing.py
archetypal/tabulardata.py
archetypal/template/__init__.py
archetypal/template/building_template.py
archetypal/template/conditioning.py
archetypal/template/constructions/__init__.py
archetypal/template/constructions/base_construction.py
archetypal/template/constructions/internal_mass.py
archetypal/template/constructions/opaque_construction.py
archetypal/template/constructions/window_construction.py
archetypal/template/dhw.py
archetypal/template/load.py
archetypal/template/materials/__init__.py
archetypal/template/materials/gas_layer.py
archetypal/template/materials/gas_material.py
archetypal/template/materials/glazing_material.py
archetypal/template/materials/material_base.py
archetypal/template/materials/material_layer.py
archetypal/template/materials/nomass_material.py
archetypal/template/materials/opaque_material.py
archetypal/template/schedule.py
archetypal/template/structure.py
archetypal/template/umi_base.py
archetypal/template/ventilation.py
archetypal/template/window_setting.py
archetypal/template/zone_construction_set.py
archetypal/template/zonedefinition.py
archetypal/umi_template.py
archetypal/utils.py
archetypal-2.18.9.dist-info/LICENSE.md
archetypal-2.18.9.dist-info/METADATA
archetypal-2.18.9.dist-info/WHEEL
archetypal-2.18.9.dist-info/entry_points.txt
archetypal-2.18.9.dist-info/RECORD
