Metadata-Version: 2.3
Name: archetypal
Version: 2.18.9
Summary: Retrieve, construct, simulate, convert and analyse building archetypes
License: MIT
Author: Samuel Letellier-Duchesne
Author-email: samuelduchesne@me.com
Requires-Python: >=3.9,<4.0
Classifier: License :: OSI Approved :: MIT License
Classifier: Programming Language :: Python :: 3
Classifier: Programming Language :: Python :: 3.9
Classifier: Programming Language :: Python :: 3.10
Classifier: Programming Language :: Python :: 3.11
Classifier: Programming Language :: Python :: 3.12
Classifier: Programming Language :: Python :: 3.13
Requires-Dist: beautifulsoup4 (<=4.8)
Requires-Dist: click (>=8.1.7,<9.0.0)
Requires-Dist: contourpy (>=1.2.1,<2.0.0)
Requires-Dist: coolprop (>=6.6.0,<7.0.0)
Requires-Dist: cycler (>=0.12.1,<0.13.0)
Requires-Dist: decorator (>=5.1.1,<6.0.0)
Requires-Dist: deprecation (>=2.1.0,<3.0.0)
Requires-Dist: energy_pandas (>=0.4.1,<0.5.0)
Requires-Dist: eppy (>=0.5.63,<0.6.0)
Requires-Dist: esoreader (>=1.2.3,<2.0.0)
Requires-Dist: eval-type-backport (>=0.2.0,<0.3.0) ; python_version == "3.9"
Requires-Dist: fonttools (>=4.53.0,<5.0.0)
Requires-Dist: future (>=1.0.0,<2.0.0)
Requires-Dist: kiwisolver (>=1.4.5,<2.0.0)
Requires-Dist: lxml (>=5.2.2,<6.0.0)
Requires-Dist: matplotlib (>=3.4,<4.0)
Requires-Dist: munch (>=4.0.0,<5.0.0)
Requires-Dist: networkx (<3)
Requires-Dist: numpy (>=2.0.2,<3.0.0) ; python_full_version <= "3.9.0"
Requires-Dist: numpy (>=2.1.1,<3.0.0) ; python_version == "3.10"
Requires-Dist: outdated (>=0.2.2,<0.3.0)
Requires-Dist: packaging (>=24.1,<25.0)
Requires-Dist: pandas (>=2.0.3)
Requires-Dist: path (>=17.1.0)
Requires-Dist: pillow (>=10.3.0,<11.0.0)
Requires-Dist: pyclipper (>=1.3.0.post5,<2.0.0)
Requires-Dist: pycountry (>=24.6.1,<25.0.0)
Requires-Dist: pydantic-settings (>=2.3.2,<3.0.0)
Requires-Dist: pydot3k (>=1.0.17,<2.0.0)
Requires-Dist: pyparsing (>=3.1.2,<4.0.0)
Requires-Dist: pypoly2tri (>=0.0.3,<0.0.4)
Requires-Dist: python-dateutil (>=2.9.0.post0,<3.0.0)
Requires-Dist: requests (>=2.32.3,<3.0.0)
Requires-Dist: scikit-learn (>=1.5.0,<2.0.0)
Requires-Dist: shapely (>=2.0.6,<3.0.0)
Requires-Dist: sigfig (>=1.3.3,<2.0.0)
Requires-Dist: six (>=1.16.0,<2.0.0)
Requires-Dist: soupsieve (>=2.5,<3.0)
Requires-Dist: tomli (>=2.0.1,<3.0.0)
Requires-Dist: tqdm (>=4.66.4,<5.0.0)
Requires-Dist: transforms3d (>=0.4.1,<0.5.0)
Requires-Dist: typing-extensions (>=4.12.2,<5.0.0)
Requires-Dist: validator-collection (>=1.5.0,<2.0.0)
